truedriver/__init__.py
truedriver/_version.py
truedriver/cdp/README.md
truedriver/cdp/__init__.py
truedriver/cdp/accessibility.py
truedriver/cdp/animation.py
truedriver/cdp/audits.py
truedriver/cdp/autofill.py
truedriver/cdp/background_service.py
truedriver/cdp/bluetooth_emulation.py
truedriver/cdp/browser.py
truedriver/cdp/cache_storage.py
truedriver/cdp/cast.py
truedriver/cdp/console.py
truedriver/cdp/css.py
truedriver/cdp/debugger.py
truedriver/cdp/device_access.py
truedriver/cdp/device_orientation.py
truedriver/cdp/dom.py
truedriver/cdp/dom_debugger.py
truedriver/cdp/dom_snapshot.py
truedriver/cdp/dom_storage.py
truedriver/cdp/emulation.py
truedriver/cdp/event_breakpoints.py
truedriver/cdp/extensions.py
truedriver/cdp/fed_cm.py
truedriver/cdp/fetch.py
truedriver/cdp/file_system.py
truedriver/cdp/headless_experimental.py
truedriver/cdp/heap_profiler.py
truedriver/cdp/indexed_db.py
truedriver/cdp/input_.py
truedriver/cdp/inspector.py
truedriver/cdp/io.py
truedriver/cdp/layer_tree.py
truedriver/cdp/log.py
truedriver/cdp/media.py
truedriver/cdp/memory.py
truedriver/cdp/network.py
truedriver/cdp/overlay.py
truedriver/cdp/page.py
truedriver/cdp/performance.py
truedriver/cdp/performance_timeline.py
truedriver/cdp/preload.py
truedriver/cdp/profiler.py
truedriver/cdp/pwa.py
truedriver/cdp/py.typed
truedriver/cdp/runtime.py
truedriver/cdp/schema.py
truedriver/cdp/security.py
truedriver/cdp/service_worker.py
truedriver/cdp/storage.py
truedriver/cdp/system_info.py
truedriver/cdp/target.py
truedriver/cdp/tethering.py
truedriver/cdp/tracing.py
truedriver/cdp/util.py
truedriver/cdp/web_audio.py
truedriver/cdp/web_authn.py
truedriver/core/_contradict.py
truedriver/core/browser.py
truedriver/core/cloudflare.py
truedriver/core/config.py
truedriver/core/connection.py
truedriver/core/element.py
truedriver/core/expect.py
truedriver/core/intercept.py
truedriver/core/keys.py
truedriver/core/tab.py
truedriver/core/util.py
truedriver-0.1.4.dist-info/METADATA
truedriver-0.1.4.dist-info/WHEEL
truedriver-0.1.4.dist-info/licenses/LICENSE
truedriver-0.1.4.dist-info/RECORD
